LICENSE.txt
README.md
docker_healthchecker.py
setup.cfg
setup.py
docker_healthchecker.egg-info/PKG-INFO
docker_healthchecker.egg-info/SOURCES.txt
docker_healthchecker.egg-info/dependency_links.txt
docker_healthchecker.egg-info/entry_points.txt
docker_healthchecker.egg-info/top_level.txt