Metadata-Version: 2.1
Name: docker-healthchecker
Version: 0.3.0
Summary: Wait for Docker health checks
Home-page: https://github.com/nvllsvm/docker-healthchecker
Author: Andrew Rabert
Author-email: ar@nullsum.net
License: UNKNOWN
Platform: UNKNOWN
License-File: LICENSE.txt
